scripts/generate_release_notes.py
serilux/__init__.py
serilux/py.typed
serilux/serializable.py
serilux-0.2.1.dist-info/licenses/LICENSE
serilux-0.2.1.dist-info/METADATA
serilux-0.2.1.dist-info/WHEEL
serilux-0.2.1.dist-info/top_level.txt
serilux-0.2.1.dist-info/RECORD
