Metadata-Version: 2.4
Name: serilux
Version: 0.2.1
Summary: A powerful serialization framework for Python objects with automatic type registration and validation
Author: Serilux Team
License-Expression: Apache-2.0
Project-URL: Homepage, https://github.com/lzjever/serilux
Project-URL: Documentation, https://serilux.readthedocs.io
Project-URL: Repository, https://github.com/lzjever/serilux
Project-URL: Issues, https://github.com/lzjever/serilux/issues
Keywords: serialization,deserialization,serializable,json,persistence
Classifier: Development Status :: 4 - Beta
Classifier: Intended Audience :: Developers
Classifier: Programming Language :: Python :: 3
Classifier: Programming Language :: Python :: 3.7
Classifier: Programming Language :: Python :: 3.8
Classifier: Programming Language :: Python :: 3.9
Classifier: Programming Language :: Python :: 3.10
Classifier: Programming Language :: Python :: 3.11
Classifier: Topic :: Software Development :: Libraries :: Python Modules
Requires-Python: >=3.7
License-File: LICENSE
Provides-Extra: dev
Requires-Dist: pytest>=7.0.0; extra == "dev"
Requires-Dist: pytest-cov>=4.0.0; extra == "dev"
Requires-Dist: sphinx>=5.0.0; extra == "dev"
Requires-Dist: sphinx-rtd-theme>=1.0.0; extra == "dev"
Requires-Dist: black>=22.0.0; extra == "dev"
Requires-Dist: flake8>=5.0.0; extra == "dev"
Requires-Dist: mypy>=0.991; extra == "dev"
Provides-Extra: docs
Requires-Dist: sphinx>=5.0.0; extra == "docs"
Requires-Dist: sphinx-rtd-theme>=1.0.0; extra == "docs"
Requires-Dist: furo>=2024.1.0; extra == "docs"
Requires-Dist: sphinx-autodoc-typehints>=1.19.0; extra == "docs"
Requires-Dist: sphinx-copybutton>=0.5.0; extra == "docs"
Requires-Dist: sphinx-design>=0.5.0; extra == "docs"
Dynamic: license-file
